kiwiki/__init__.py
kiwiki/kiwiki.py
kiwiki_client-0.1.2.dist-info/LICENSE
kiwiki_client-0.1.2.dist-info/METADATA
kiwiki_client-0.1.2.dist-info/WHEEL
kiwiki_client-0.1.2.dist-info/top_level.txt
kiwiki_client-0.1.2.dist-info/RECORD
